desdeov2/__init__.py
desdeov2/logger.cfg
desdeov2/manager/__init__.py
desdeov2/methods/InteractiveMethod.py
desdeov2/methods/Nautilus.py
desdeov2/methods/Nimbus.py
desdeov2/methods/__init__.py
desdeov2/problem/Constraint.py
desdeov2/problem/Objective.py
desdeov2/problem/Problem.py
desdeov2/problem/Variable.py
desdeov2/problem/__init__.py
desdeov2/solver/ASF.py
desdeov2/solver/NumericalMethods.py
desdeov2/solver/PointSolver.py
desdeov2/solver/ScalarSolver.py
desdeov2/solver/__init__.py
desdeov2/utils/__init__.py
desdeov2/utils/frozen.py
desdeov2-0.1.1.dist-info/LICENSE
desdeov2-0.1.1.dist-info/WHEEL
desdeov2-0.1.1.dist-info/METADATA
desdeov2-0.1.1.dist-info/RECORD
